[
    {
        "name": "FPS-256x256",
        "quantity": "frequency",
        "unit": "Hz",
        "value": 50.946638625465155
    },
    {
        "name": "FPS-512x512",
        "quantity": "frequency",
        "unit": "Hz",
        "value": 25.74866807990903
    },
    {
        "name": "FPS-768x768",
        "quantity": "frequency",
        "unit": "Hz",
        "value": 13.615640562036663
    },
    {
        "name": "FPS-1024x1024",
        "quantity": "frequency",
        "unit": "Hz",
        "value": 8.262770369196838
    }
]