[
    {
        "name": "FPS-256x256",
        "quantity": "frequency",
        "unit": "Hz",
        "value": 85.53788865210615
    },
    {
        "name": "FPS-512x512",
        "quantity": "frequency",
        "unit": "Hz",
        "value": 32.820403852454625
    },
    {
        "name": "FPS-768x768",
        "quantity": "frequency",
        "unit": "Hz",
        "value": 15.438503524160977
    },
    {
        "name": "FPS-1024x1024",
        "quantity": "frequency",
        "unit": "Hz",
        "value": 8.902410693233877
    }
]