[
    {
        "name": "FPS-size-1024-insts-4096-res-64",
        "quantity": "frequency",
        "unit": "Hz",
        "value": 20.555505412396627
    },
    {
        "name": "FPS-size-1024-insts-4096-res-32",
        "quantity": "frequency",
        "unit": "Hz",
        "value": 25.85437707958692
    },
    {
        "name": "FPS-size-1024-insts-4096-res-16",
        "quantity": "frequency",
        "unit": "Hz",
        "value": 24.828545121215726
    },
    {
        "name": "FPS-size-1024-insts-512-res-64",
        "quantity": "frequency",
        "unit": "Hz",
        "value": 51.199129702293575
    },
    {
        "name": "FPS-size-1024-insts-512-res-32",
        "quantity": "frequency",
        "unit": "Hz",
        "value": 82.77929955278377
    },
    {
        "name": "FPS-size-1024-insts-512-res-16",
        "quantity": "frequency",
        "unit": "Hz",
        "value": 64.1131610046177
    },
    {
        "name": "FPS-size-1024-insts-64-res-64",
        "quantity": "frequency",
        "unit": "Hz",
        "value": 78.6568485763079
    },
    {
        "name": "FPS-size-1024-insts-64-res-32",
        "quantity": "frequency",
        "unit": "Hz",
        "value": 99.70577143705592
    },
    {
        "name": "FPS-size-1024-insts-64-res-16",
        "quantity": "frequency",
        "unit": "Hz",
        "value": 73.64915353304721
    },
    {
        "name": "FPS-size-512-insts-4096-res-64",
        "quantity": "frequency",
        "unit": "Hz",
        "value": 27.51821167321725
    },
    {
        "name": "FPS-size-512-insts-4096-res-32",
        "quantity": "frequency",
        "unit": "Hz",
        "value": 31.50012171593028
    },
    {
        "name": "FPS-size-512-insts-4096-res-16",
        "quantity": "frequency",
        "unit": "Hz",
        "value": 31.58278269341065
    },
    {
        "name": "FPS-size-512-insts-512-res-64",
        "quantity": "frequency",
        "unit": "Hz",
        "value": 100.98070328002024
    },
    {
        "name": "FPS-size-512-insts-512-res-32",
        "quantity": "frequency",
        "unit": "Hz",
        "value": 85.59758839922586
    },
    {
        "name": "FPS-size-512-insts-512-res-16",
        "quantity": "frequency",
        "unit": "Hz",
        "value": 107.09716401877174
    },
    {
        "name": "FPS-size-512-insts-64-res-64",
        "quantity": "frequency",
        "unit": "Hz",
        "value": 93.85840878454472
    },
    {
        "name": "FPS-size-512-insts-64-res-32",
        "quantity": "frequency",
        "unit": "Hz",
        "value": 88.12121115607746
    },
    {
        "name": "FPS-size-512-insts-64-res-16",
        "quantity": "frequency",
        "unit": "Hz",
        "value": 108.70223852004102
    },
    {
        "name": "FPS-size-256-insts-4096-res-64",
        "quantity": "frequency",
        "unit": "Hz",
        "value": 25.226514966650655
    },
    {
        "name": "FPS-size-256-insts-4096-res-32",
        "quantity": "frequency",
        "unit": "Hz",
        "value": 25.815583632645033
    },
    {
        "name": "FPS-size-256-insts-4096-res-16",
        "quantity": "frequency",
        "unit": "Hz",
        "value": 26.30841975363227
    },
    {
        "name": "FPS-size-256-insts-512-res-64",
        "quantity": "frequency",
        "unit": "Hz",
        "value": 77.18609369954898
    },
    {
        "name": "FPS-size-256-insts-512-res-32",
        "quantity": "frequency",
        "unit": "Hz",
        "value": 92.18727314674997
    },
    {
        "name": "FPS-size-256-insts-512-res-16",
        "quantity": "frequency",
        "unit": "Hz",
        "value": 98.92021345938674
    },
    {
        "name": "FPS-size-256-insts-64-res-64",
        "quantity": "frequency",
        "unit": "Hz",
        "value": 96.25218453335567
    },
    {
        "name": "FPS-size-256-insts-64-res-32",
        "quantity": "frequency",
        "unit": "Hz",
        "value": 105.64655152684698
    },
    {
        "name": "FPS-size-256-insts-64-res-16",
        "quantity": "frequency",
        "unit": "Hz",
        "value": 83.0694501943426
    }
]