[
    {
        "name": "s39i3p04.png-time",
        "quantity": "frequency",
        "unit": "Hz",
        "value": 0.0072170279890997335
    },
    {
        "name": "s38i3p04.png-time",
        "quantity": "frequency",
        "unit": "Hz",
        "value": 0.01004274599836208
    },
    {
        "name": "s05n3p02.png-time",
        "quantity": "frequency",
        "unit": "Hz",
        "value": 0.007704428004217334
    },
    {
        "name": "cs5n2c08.png-time",
        "quantity": "frequency",
        "unit": "Hz",
        "value": 0.004230997001286596
    },
    {
        "name": "bgwn6a08.png-time",
        "quantity": "frequency",
        "unit": "Hz",
        "value": 0.004328195995185524
    },
    {
        "name": "basn3p02.png-time",
        "quantity": "frequency",
        "unit": "Hz",
        "value": 0.0032493019971298054
    },
    {
        "name": "bggn4a16.png-time",
        "quantity": "frequency",
        "unit": "Hz",
        "value": 0.004461952004930936
    },
    {
        "name": "basi0g08.png-time",
        "quantity": "frequency",
        "unit": "Hz",
        "value": 0.003322924007079564
    },
    {
        "name": "bgbn4a08.png-time",
        "quantity": "frequency",
        "unit": "Hz",
        "value": 0.00464040799124632
    },
    {
        "name": "basn4a16.png-time",
        "quantity": "frequency",
        "unit": "Hz",
        "value": 0.0038233179948292673
    },
    {
        "name": "s04n3p01.png-time",
        "quantity": "frequency",
        "unit": "Hz",
        "value": 0.0037925180076854303
    },
    {
        "name": "s33i3p04.png-time",
        "quantity": "frequency",
        "unit": "Hz",
        "value": 0.007915870999568142
    },
    {
        "name": "s32i3p04.png-time",
        "quantity": "frequency",
        "unit": "Hz",
        "value": 0.0075801200000569224
    },
    {
        "name": "cm0n0g04.png-time",
        "quantity": "frequency",
        "unit": "Hz",
        "value": 0.0033606069919187576
    },
    {
        "name": "basn3p01.png-time",
        "quantity": "frequency",
        "unit": "Hz",
        "value": 0.005734416001359932
    },
    {
        "name": "basi2c08.png-time",
        "quantity": "frequency",
        "unit": "Hz",
        "value": 0.0061197030008770525
    },
    {
        "name": "bgyn6a16.png-time",
        "quantity": "frequency",
        "unit": "Hz",
        "value": 0.004896960992482491
    },
    {
        "name": "ps1n2c16.png-time",
        "quantity": "frequency",
        "unit": "Hz",
        "value": 0.0038308810035232455
    },
    {
        "name": "g03n3p04.png-time",
        "quantity": "frequency",
        "unit": "Hz",
        "value": 0.004096182994544506
    },
    {
        "name": "basn6a16.png-time",
        "quantity": "frequency",
        "unit": "Hz",
        "value": 0.00473003598744981
    },
    {
        "name": "ccwn3p08.png-time",
        "quantity": "frequency",
        "unit": "Hz",
        "value": 0.004403281011036597
    },
    {
        "name": "oi1n2c16.png-time",
        "quantity": "frequency",
        "unit": "Hz",
        "value": 0.005106989003252238
    },
    {
        "name": "f03n0g08.png-time",
        "quantity": "frequency",
        "unit": "Hz",
        "value": 0.004784204007592052
    },
    {
        "name": "f02n0g08.png-time",
        "quantity": "frequency",
        "unit": "Hz",
        "value": 0.0031740020058350638
    },
    {
        "name": "oi1n0g16.png-time",
        "quantity": "frequency",
        "unit": "Hz",
        "value": 0.003374342995812185
    },
    {
        "name": "s06i3p02.png-time",
        "quantity": "frequency",
        "unit": "Hz",
        "value": 0.00405417600995861
    },
    {
        "name": "s07i3p02.png-time",
        "quantity": "frequency",
        "unit": "Hz",
        "value": 0.004199798000627197
    },
    {
        "name": "cdhn2c08.png-time",
        "quantity": "frequency",
        "unit": "Hz",
        "value": 0.0034383189922664315
    },
    {
        "name": "f03n2c08.png-time",
        "quantity": "frequency",
        "unit": "Hz",
        "value": 0.009882583006401546
    },
    {
        "name": "f02n2c08.png-time",
        "quantity": "frequency",
        "unit": "Hz",
        "value": 0.004301147986552678
    },
    {
        "name": "cs8n3p08.png-time",
        "quantity": "frequency",
        "unit": "Hz",
        "value": 0.004917934013064951
    },
    {
        "name": "basn3p04.png-time",
        "quantity": "frequency",
        "unit": "Hz",
        "value": 0.004907177004497498
    },
    {
        "name": "g04n0g16.png-time",
        "quantity": "frequency",
        "unit": "Hz",
        "value": 0.004187436992651783
    },
    {
        "name": "g05n0g16.png-time",
        "quantity": "frequency",
        "unit": "Hz",
        "value": 0.004608153001754545
    },
    {
        "name": "cthn0g04.png-time",
        "quantity": "frequency",
        "unit": "Hz",
        "value": 0.004415215997141786
    },
    {
        "name": "cs3n3p08.png-time",
        "quantity": "frequency",
        "unit": "Hz",
        "value": 0.004324369001551531
    },
    {
        "name": "bgai4a08.png-time",
        "quantity": "frequency",
        "unit": "Hz",
        "value": 0.003961458001867868
    },
    {
        "name": "basi3p08.png-time",
        "quantity": "frequency",
        "unit": "Hz",
        "value": 0.004290728000341915
    },
    {
        "name": "g05n3p04.png-time",
        "quantity": "frequency",
        "unit": "Hz",
        "value": 0.005127893993631005
    },
    {
        "name": "g04n3p04.png-time",
        "quantity": "frequency",
        "unit": "Hz",
        "value": 0.004408912005601451
    },
    {
        "name": "bgan6a16.png-time",
        "quantity": "frequency",
        "unit": "Hz",
        "value": 0.0030197530140867457
    },
    {
        "name": "f04n0g08.png-time",
        "quantity": "frequency",
        "unit": "Hz",
        "value": 0.005608146995655261
    },
    {
        "name": "ct0n0g04.png-time",
        "quantity": "frequency",
        "unit": "Hz",
        "value": 0.003812137001659721
    },
    {
        "name": "ct1n0g04.png-time",
        "quantity": "frequency",
        "unit": "Hz",
        "value": 0.004356939010904171
    },
    {
        "name": "f04n2c08.png-time",
        "quantity": "frequency",
        "unit": "Hz",
        "value": 0.003670768011943437
    },
    {
        "name": "cten0g04.png-time",
        "quantity": "frequency",
        "unit": "Hz",
        "value": 0.004820759000722319
    },
    {
        "name": "g03n0g16.png-time",
        "quantity": "frequency",
        "unit": "Hz",
        "value": 0.0030007550085429102
    },
    {
        "name": "basn2c16.png-time",
        "quantity": "frequency",
        "unit": "Hz",
        "value": 0.002617585996631533
    },
    {
        "name": "s40n3p04.png-time",
        "quantity": "frequency",
        "unit": "Hz",
        "value": 0.0075016030023107305
    },
    {
        "name": "basi4a08.png-time",
        "quantity": "frequency",
        "unit": "Hz",
        "value": 0.0072123800055123866
    },
    {
        "name": "cs5n3p08.png-time",
        "quantity": "frequency",
        "unit": "Hz",
        "value": 0.005152439000084996
    },
    {
        "name": "s37n3p04.png-time",
        "quantity": "frequency",
        "unit": "Hz",
        "value": 0.008367781003471464
    },
    {
        "name": "s36n3p04.png-time",
        "quantity": "frequency",
        "unit": "Hz",
        "value": 0.007441420995746739
    },
    {
        "name": "s01i3p01.png-time",
        "quantity": "frequency",
        "unit": "Hz",
        "value": 0.008696824996150099
    },
    {
        "name": "g07n2c08.png-time",
        "quantity": "frequency",
        "unit": "Hz",
        "value": 0.00498612699448131
    },
    {
        "name": "basn0g02.png-time",
        "quantity": "frequency",
        "unit": "Hz",
        "value": 0.007031931992969476
    },
    {
        "name": "basn0g16.png-time",
        "quantity": "frequency",
        "unit": "Hz",
        "value": 0.001090392004698515
    },
    {
        "name": "g25n2c08.png-time",
        "quantity": "frequency",
        "unit": "Hz",
        "value": 0.004996938994736411
    },
    {
        "name": "PngSuite.png-time",
        "quantity": "frequency",
        "unit": "Hz",
        "value": 0.015172776998952031
    },
    {
        "name": "exif2c08.png-time",
        "quantity": "frequency",
        "unit": "Hz",
        "value": 0.010895536994212307
    },
    {
        "name": "basi6a08.png-time",
        "quantity": "frequency",
        "unit": "Hz",
        "value": 0.004564592003589496
    },
    {
        "name": "z03n2c08.png-time",
        "quantity": "frequency",
        "unit": "Hz",
        "value": 0.003407850002986379
    },
    {
        "name": "s08n3p02.png-time",
        "quantity": "frequency",
        "unit": "Hz",
        "value": 0.0037626949924742803
    },
    {
        "name": "s09n3p02.png-time",
        "quantity": "frequency",
        "unit": "Hz",
        "value": 0.003059117996599525
    },
    {
        "name": "pp0n6a08.png-time",
        "quantity": "frequency",
        "unit": "Hz",
        "value": 0.004016541002783924
    },
    {
        "name": "cs8n2c08.png-time",
        "quantity": "frequency",
        "unit": "Hz",
        "value": 0.004705817002104595
    },
    {
        "name": "f99n0g04.png-time",
        "quantity": "frequency",
        "unit": "Hz",
        "value": 0.003979384986450896
    },
    {
        "name": "ps2n0g08.png-time",
        "quantity": "frequency",
        "unit": "Hz",
        "value": 0.003270033994340338
    },
    {
        "name": "s34i3p04.png-time",
        "quantity": "frequency",
        "unit": "Hz",
        "value": 0.011859860009280965
    },
    {
        "name": "s35i3p04.png-time",
        "quantity": "frequency",
        "unit": "Hz",
        "value": 0.008184115999029018
    },
    {
        "name": "ctzn0g04.png-time",
        "quantity": "frequency",
        "unit": "Hz",
        "value": 0.007682928000576794
    },
    {
        "name": "s03n3p01.png-time",
        "quantity": "frequency",
        "unit": "Hz",
        "value": 0.004343546999734826
    },
    {
        "name": "s02n3p01.png-time",
        "quantity": "frequency",
        "unit": "Hz",
        "value": 0.004768697006511502
    },
    {
        "name": "z09n2c08.png-time",
        "quantity": "frequency",
        "unit": "Hz",
        "value": 0.004232897990732454
    },
    {
        "name": "g10n2c08.png-time",
        "quantity": "frequency",
        "unit": "Hz",
        "value": 0.0043153279984835535
    },
    {
        "name": "cm7n0g04.png-time",
        "quantity": "frequency",
        "unit": "Hz",
        "value": 0.005006502993637696
    },
    {
        "name": "ccwn2c08.png-time",
        "quantity": "frequency",
        "unit": "Hz",
        "value": 0.004384808999020606
    },
    {
        "name": "basn0g04.png-time",
        "quantity": "frequency",
        "unit": "Hz",
        "value": 0.00319275600486435
    },
    {
        "name": "g07n0g16.png-time",
        "quantity": "frequency",
        "unit": "Hz",
        "value": 0.004828892007935792
    },
    {
        "name": "basi3p01.png-time",
        "quantity": "frequency",
        "unit": "Hz",
        "value": 0.004430642991792411
    },
    {
        "name": "basn2c08.png-time",
        "quantity": "frequency",
        "unit": "Hz",
        "value": 0.0033661860070424154
    },
    {
        "name": "oi9n2c16.png-time",
        "quantity": "frequency",
        "unit": "Hz",
        "value": 0.00883958199119661
    },
    {
        "name": "basi4a16.png-time",
        "quantity": "frequency",
        "unit": "Hz",
        "value": 0.00389183200604748
    },
    {
        "name": "s04i3p01.png-time",
        "quantity": "frequency",
        "unit": "Hz",
        "value": 0.004086995992111042
    },
    {
        "name": "ctjn0g04.png-time",
        "quantity": "frequency",
        "unit": "Hz",
        "value": 0.003614536006352864
    },
    {
        "name": "s33n3p04.png-time",
        "quantity": "frequency",
        "unit": "Hz",
        "value": 0.00856965700222645
    },
    {
        "name": "s32n3p04.png-time",
        "quantity": "frequency",
        "unit": "Hz",
        "value": 0.008011120997252874
    },
    {
        "name": "oi9n0g16.png-time",
        "quantity": "frequency",
        "unit": "Hz",
        "value": 0.003658393005025573
    },
    {
        "name": "g03n2c08.png-time",
        "quantity": "frequency",
        "unit": "Hz",
        "value": 0.0042392069881316274
    },
    {
        "name": "basn0g08.png-time",
        "quantity": "frequency",
        "unit": "Hz",
        "value": 0.00368372599768918
    },
    {
        "name": "basi3p02.png-time",
        "quantity": "frequency",
        "unit": "Hz",
        "value": 0.0040767099999357015
    },
    {
        "name": "tp0n2c08.png-time",
        "quantity": "frequency",
        "unit": "Hz",
        "value": 0.0041752010001800954
    },
    {
        "name": "bgan6a08.png-time",
        "quantity": "frequency",
        "unit": "Hz",
        "value": 0.0034895400021923706
    },
    {
        "name": "oi2n2c16.png-time",
        "quantity": "frequency",
        "unit": "Hz",
        "value": 0.005117955995956436
    },
    {
        "name": "f00n0g08.png-time",
        "quantity": "frequency",
        "unit": "Hz",
        "value": 0.003923260010196827
    },
    {
        "name": "f01n0g08.png-time",
        "quantity": "frequency",
        "unit": "Hz",
        "value": 0.004385484993690625
    },
    {
        "name": "s05i3p02.png-time",
        "quantity": "frequency",
        "unit": "Hz",
        "value": 0.003775108008994721
    },
    {
        "name": "oi2n0g16.png-time",
        "quantity": "frequency",
        "unit": "Hz",
        "value": 0.004392009010189213
    },
    {
        "name": "f00n2c08.png-time",
        "quantity": "frequency",
        "unit": "Hz",
        "value": 0.0036941180005669594
    },
    {
        "name": "f01n2c08.png-time",
        "quantity": "frequency",
        "unit": "Hz",
        "value": 0.004073971998877823
    },
    {
        "name": "s39n3p04.png-time",
        "quantity": "frequency",
        "unit": "Hz",
        "value": 0.011341839010128751
    },
    {
        "name": "s38n3p04.png-time",
        "quantity": "frequency",
        "unit": "Hz",
        "value": 0.007083285003318451
    },
    {
        "name": "tp0n0g08.png-time",
        "quantity": "frequency",
        "unit": "Hz",
        "value": 0.009239894992788322
    },
    {
        "name": "cdun2c08.png-time",
        "quantity": "frequency",
        "unit": "Hz",
        "value": 0.005323446006514132
    },
    {
        "name": "g10n0g16.png-time",
        "quantity": "frequency",
        "unit": "Hz",
        "value": 0.0038268290081759915
    },
    {
        "name": "ch1n3p04.png-time",
        "quantity": "frequency",
        "unit": "Hz",
        "value": 0.004177269001957029
    },
    {
        "name": "ps2n2c16.png-time",
        "quantity": "frequency",
        "unit": "Hz",
        "value": 0.004539731991826557
    },
    {
        "name": "basi3p04.png-time",
        "quantity": "frequency",
        "unit": "Hz",
        "value": 0.005145019997144118
    },
    {
        "name": "cs3n2c16.png-time",
        "quantity": "frequency",
        "unit": "Hz",
        "value": 0.003674956999020651
    },
    {
        "name": "s06n3p02.png-time",
        "quantity": "frequency",
        "unit": "Hz",
        "value": 0.0036732199951075017
    },
    {
        "name": "s07n3p02.png-time",
        "quantity": "frequency",
        "unit": "Hz",
        "value": 0.004296633007470518
    },
    {
        "name": "g25n0g16.png-time",
        "quantity": "frequency",
        "unit": "Hz",
        "value": 0.0036957239935873076
    },
    {
        "name": "z06n2c08.png-time",
        "quantity": "frequency",
        "unit": "Hz",
        "value": 0.003708235002704896
    },
    {
        "name": "basi6a16.png-time",
        "quantity": "frequency",
        "unit": "Hz",
        "value": 0.005349250001017936
    },
    {
        "name": "cm9n0g04.png-time",
        "quantity": "frequency",
        "unit": "Hz",
        "value": 0.003650650003692135
    },
    {
        "name": "cdsn2c08.png-time",
        "quantity": "frequency",
        "unit": "Hz",
        "value": 0.0037674089981010184
    },
    {
        "name": "ps1n0g08.png-time",
        "quantity": "frequency",
        "unit": "Hz",
        "value": 0.008276130000012927
    },
    {
        "name": "basi0g02.png-time",
        "quantity": "frequency",
        "unit": "Hz",
        "value": 0.003748746996279806
    },
    {
        "name": "basi0g16.png-time",
        "quantity": "frequency",
        "unit": "Hz",
        "value": 0.004191070998786017
    },
    {
        "name": "basn4a08.png-time",
        "quantity": "frequency",
        "unit": "Hz",
        "value": 0.00467360598850064
    },
    {
        "name": "s37i3p04.png-time",
        "quantity": "frequency",
        "unit": "Hz",
        "value": 0.009281432998250239
    },
    {
        "name": "s36i3p04.png-time",
        "quantity": "frequency",
        "unit": "Hz",
        "value": 0.008401323008001782
    },
    {
        "name": "s01n3p01.png-time",
        "quantity": "frequency",
        "unit": "Hz",
        "value": 0.00705358300183434
    },
    {
        "name": "s40i3p04.png-time",
        "quantity": "frequency",
        "unit": "Hz",
        "value": 0.007207357004517689
    },
    {
        "name": "g25n3p04.png-time",
        "quantity": "frequency",
        "unit": "Hz",
        "value": 0.007524293992901221
    },
    {
        "name": "tp0n3p08.png-time",
        "quantity": "frequency",
        "unit": "Hz",
        "value": 0.003562010999303311
    },
    {
        "name": "basi2c16.png-time",
        "quantity": "frequency",
        "unit": "Hz",
        "value": 0.003817983000772074
    },
    {
        "name": "pp0n2c16.png-time",
        "quantity": "frequency",
        "unit": "Hz",
        "value": 0.003104136005276814
    },
    {
        "name": "g10n3p04.png-time",
        "quantity": "frequency",
        "unit": "Hz",
        "value": 0.004233986008330248
    },
    {
        "name": "basn3p08.png-time",
        "quantity": "frequency",
        "unit": "Hz",
        "value": 0.007769383009872399
    },
    {
        "name": "z00n2c08.png-time",
        "quantity": "frequency",
        "unit": "Hz",
        "value": 0.0035099000087939203
    },
    {
        "name": "basi0g04.png-time",
        "quantity": "frequency",
        "unit": "Hz",
        "value": 0.0042539389978628606
    },
    {
        "name": "s34n3p04.png-time",
        "quantity": "frequency",
        "unit": "Hz",
        "value": 0.007082512995111756
    },
    {
        "name": "s35n3p04.png-time",
        "quantity": "frequency",
        "unit": "Hz",
        "value": 0.006842653994681314
    },
    {
        "name": "s03i3p01.png-time",
        "quantity": "frequency",
        "unit": "Hz",
        "value": 0.006968032001168467
    },
    {
        "name": "s02i3p01.png-time",
        "quantity": "frequency",
        "unit": "Hz",
        "value": 0.003551521003828384
    },
    {
        "name": "s08i3p02.png-time",
        "quantity": "frequency",
        "unit": "Hz",
        "value": 0.0035665870091179386
    },
    {
        "name": "s09i3p02.png-time",
        "quantity": "frequency",
        "unit": "Hz",
        "value": 0.00309617500170134
    },
    {
        "name": "g05n2c08.png-time",
        "quantity": "frequency",
        "unit": "Hz",
        "value": 0.0049703819968272
    },
    {
        "name": "g04n2c08.png-time",
        "quantity": "frequency",
        "unit": "Hz",
        "value": 0.004852175014093518
    },
    {
        "name": "ch2n3p08.png-time",
        "quantity": "frequency",
        "unit": "Hz",
        "value": 0.0031280039984267205
    },
    {
        "name": "bgai4a16.png-time",
        "quantity": "frequency",
        "unit": "Hz",
        "value": 0.0037313369975890964
    },
    {
        "name": "cdfn2c08.png-time",
        "quantity": "frequency",
        "unit": "Hz",
        "value": 0.004164600992226042
    },
    {
        "name": "basn6a08.png-time",
        "quantity": "frequency",
        "unit": "Hz",
        "value": 0.0038555979990633205
    },
    {
        "name": "g07n3p04.png-time",
        "quantity": "frequency",
        "unit": "Hz",
        "value": 0.003509971997118555
    },
    {
        "name": "oi4n2c16.png-time",
        "quantity": "frequency",
        "unit": "Hz",
        "value": 0.004064031003508717
    },
    {
        "name": "oi4n0g16.png-time",
        "quantity": "frequency",
        "unit": "Hz",
        "value": 0.004790601000422612
    },
    {
        "name": "ctfn0g04.png-time",
        "quantity": "frequency",
        "unit": "Hz",
        "value": 0.003483032007352449
    },
    {
        "name": "ctgn0g04.png-time",
        "quantity": "frequency",
        "unit": "Hz",
        "value": 0.0038918000063858926
    }
]