[
    {
        "name": "Gaussian-time-1x1",
        "quantity": "frequency",
        "unit": "Hz",
        "value": 0.017443850985728204
    },
    {
        "name": "Gaussian-time-3x3",
        "quantity": "frequency",
        "unit": "Hz",
        "value": 0.03200834395829588
    },
    {
        "name": "Gaussian-time-5x5",
        "quantity": "frequency",
        "unit": "Hz",
        "value": 0.03226021397858858
    },
    {
        "name": "Gaussian-time-10x10",
        "quantity": "frequency",
        "unit": "Hz",
        "value": 0.03974616201594472
    },
    {
        "name": "Gaussian-time-15x15",
        "quantity": "frequency",
        "unit": "Hz",
        "value": 0.051972584100440145
    },
    {
        "name": "Gaussian-time-30x30",
        "quantity": "frequency",
        "unit": "Hz",
        "value": 0.028395105968229473
    },
    {
        "name": "Gaussian-time-32x32",
        "quantity": "frequency",
        "unit": "Hz",
        "value": 0.03283013706095517
    },
    {
        "name": "Box-time-1x1",
        "quantity": "frequency",
        "unit": "Hz",
        "value": 0.006850204081274569
    },
    {
        "name": "Box-time-2x2",
        "quantity": "frequency",
        "unit": "Hz",
        "value": 0.02317992295138538
    },
    {
        "name": "Box-time-3x3",
        "quantity": "frequency",
        "unit": "Hz",
        "value": 0.02321216999553144
    },
    {
        "name": "Box-time-5x5",
        "quantity": "frequency",
        "unit": "Hz",
        "value": 0.0236558880424127
    },
    {
        "name": "Box-time-11x11",
        "quantity": "frequency",
        "unit": "Hz",
        "value": 0.02528792293742299
    },
    {
        "name": "Box-time-17x17",
        "quantity": "frequency",
        "unit": "Hz",
        "value": 0.026891954010352492
    },
    {
        "name": "Box-time-32x32",
        "quantity": "frequency",
        "unit": "Hz",
        "value": 0.03221526206471026
    },
    {
        "name": "Box-time-60x60",
        "quantity": "frequency",
        "unit": "Hz",
        "value": 0.042801463045179844
    }
]