[
    {
        "name": "Gaussian-time-1x1",
        "quantity": "frequency",
        "unit": "Hz",
        "value": 0.019393609996768646
    },
    {
        "name": "Gaussian-time-3x3",
        "quantity": "frequency",
        "unit": "Hz",
        "value": 0.06317846499950974
    },
    {
        "name": "Gaussian-time-5x5",
        "quantity": "frequency",
        "unit": "Hz",
        "value": 0.046930672997405054
    },
    {
        "name": "Gaussian-time-10x10",
        "quantity": "frequency",
        "unit": "Hz",
        "value": 0.07554957300089882
    },
    {
        "name": "Gaussian-time-15x15",
        "quantity": "frequency",
        "unit": "Hz",
        "value": 0.06720734299960895
    },
    {
        "name": "Gaussian-time-30x30",
        "quantity": "frequency",
        "unit": "Hz",
        "value": 0.05129665500135161
    },
    {
        "name": "Gaussian-time-32x32",
        "quantity": "frequency",
        "unit": "Hz",
        "value": 0.04392390000066371
    },
    {
        "name": "Box-time-1x1",
        "quantity": "frequency",
        "unit": "Hz",
        "value": 0.012523416000476573
    },
    {
        "name": "Box-time-2x2",
        "quantity": "frequency",
        "unit": "Hz",
        "value": 0.030483706999802962
    },
    {
        "name": "Box-time-3x3",
        "quantity": "frequency",
        "unit": "Hz",
        "value": 0.0329104529992037
    },
    {
        "name": "Box-time-5x5",
        "quantity": "frequency",
        "unit": "Hz",
        "value": 0.03277261000039289
    },
    {
        "name": "Box-time-11x11",
        "quantity": "frequency",
        "unit": "Hz",
        "value": 0.03394490400023642
    },
    {
        "name": "Box-time-17x17",
        "quantity": "frequency",
        "unit": "Hz",
        "value": 0.03306110199991963
    },
    {
        "name": "Box-time-32x32",
        "quantity": "frequency",
        "unit": "Hz",
        "value": 0.051595932000054745
    },
    {
        "name": "Box-time-60x60",
        "quantity": "frequency",
        "unit": "Hz",
        "value": 0.05757220200030133
    }
]