[
    {
        "name": "Gaussian-time-1x1",
        "quantity": "frequency",
        "unit": "Hz",
        "value": 0.03290181793272495
    },
    {
        "name": "Gaussian-time-3x3",
        "quantity": "frequency",
        "unit": "Hz",
        "value": 0.044047568924725056
    },
    {
        "name": "Gaussian-time-5x5",
        "quantity": "frequency",
        "unit": "Hz",
        "value": 0.047683209646493196
    },
    {
        "name": "Gaussian-time-10x10",
        "quantity": "frequency",
        "unit": "Hz",
        "value": 0.05713436286896467
    },
    {
        "name": "Gaussian-time-15x15",
        "quantity": "frequency",
        "unit": "Hz",
        "value": 0.09534504218026996
    },
    {
        "name": "Gaussian-time-30x30",
        "quantity": "frequency",
        "unit": "Hz",
        "value": 0.04131235694512725
    },
    {
        "name": "Gaussian-time-32x32",
        "quantity": "frequency",
        "unit": "Hz",
        "value": 0.04994274629279971
    },
    {
        "name": "Box-time-1x1",
        "quantity": "frequency",
        "unit": "Hz",
        "value": 0.01677477080374956
    },
    {
        "name": "Box-time-2x2",
        "quantity": "frequency",
        "unit": "Hz",
        "value": 0.04768880782648921
    },
    {
        "name": "Box-time-3x3",
        "quantity": "frequency",
        "unit": "Hz",
        "value": 0.036699149291962385
    },
    {
        "name": "Box-time-5x5",
        "quantity": "frequency",
        "unit": "Hz",
        "value": 0.034151401836425066
    },
    {
        "name": "Box-time-11x11",
        "quantity": "frequency",
        "unit": "Hz",
        "value": 0.03737785713747144
    },
    {
        "name": "Box-time-17x17",
        "quantity": "frequency",
        "unit": "Hz",
        "value": 0.0617087259888649
    },
    {
        "name": "Box-time-32x32",
        "quantity": "frequency",
        "unit": "Hz",
        "value": 0.04880707897245884
    },
    {
        "name": "Box-time-60x60",
        "quantity": "frequency",
        "unit": "Hz",
        "value": 0.07884614774957299
    }
]