[
    {
        "name": "s39i3p04.png-time",
        "quantity": "frequency",
        "unit": "Hz",
        "value": 0.011333733797073364
    },
    {
        "name": "s38i3p04.png-time",
        "quantity": "frequency",
        "unit": "Hz",
        "value": 0.008946208748966455
    },
    {
        "name": "s05n3p02.png-time",
        "quantity": "frequency",
        "unit": "Hz",
        "value": 0.008892673067748547
    },
    {
        "name": "cs5n2c08.png-time",
        "quantity": "frequency",
        "unit": "Hz",
        "value": 0.006117201875895262
    },
    {
        "name": "bgwn6a08.png-time",
        "quantity": "frequency",
        "unit": "Hz",
        "value": 0.00513407913967967
    },
    {
        "name": "basn3p02.png-time",
        "quantity": "frequency",
        "unit": "Hz",
        "value": 0.00484503386542201
    },
    {
        "name": "bggn4a16.png-time",
        "quantity": "frequency",
        "unit": "Hz",
        "value": 0.005413163919001818
    },
    {
        "name": "basi0g08.png-time",
        "quantity": "frequency",
        "unit": "Hz",
        "value": 0.005355379078537226
    },
    {
        "name": "bgbn4a08.png-time",
        "quantity": "frequency",
        "unit": "Hz",
        "value": 0.006929862778633833
    },
    {
        "name": "basn4a16.png-time",
        "quantity": "frequency",
        "unit": "Hz",
        "value": 0.005567749962210655
    },
    {
        "name": "s04n3p01.png-time",
        "quantity": "frequency",
        "unit": "Hz",
        "value": 0.005532616749405861
    },
    {
        "name": "s33i3p04.png-time",
        "quantity": "frequency",
        "unit": "Hz",
        "value": 0.00900147994980216
    },
    {
        "name": "s32i3p04.png-time",
        "quantity": "frequency",
        "unit": "Hz",
        "value": 0.007481108885258436
    },
    {
        "name": "cm0n0g04.png-time",
        "quantity": "frequency",
        "unit": "Hz",
        "value": 0.005105610005557537
    },
    {
        "name": "basn3p01.png-time",
        "quantity": "frequency",
        "unit": "Hz",
        "value": 0.009817597921937704
    },
    {
        "name": "basi2c08.png-time",
        "quantity": "frequency",
        "unit": "Hz",
        "value": 0.005132363177835941
    },
    {
        "name": "bgyn6a16.png-time",
        "quantity": "frequency",
        "unit": "Hz",
        "value": 0.004299165681004524
    },
    {
        "name": "ps1n2c16.png-time",
        "quantity": "frequency",
        "unit": "Hz",
        "value": 0.0054517341777682304
    },
    {
        "name": "g03n3p04.png-time",
        "quantity": "frequency",
        "unit": "Hz",
        "value": 0.0039882599376142025
    },
    {
        "name": "basn6a16.png-time",
        "quantity": "frequency",
        "unit": "Hz",
        "value": 0.004455369897186756
    },
    {
        "name": "ccwn3p08.png-time",
        "quantity": "frequency",
        "unit": "Hz",
        "value": 0.003772967029362917
    },
    {
        "name": "oi1n2c16.png-time",
        "quantity": "frequency",
        "unit": "Hz",
        "value": 0.00476072495803237
    },
    {
        "name": "f03n0g08.png-time",
        "quantity": "frequency",
        "unit": "Hz",
        "value": 0.004291879013180733
    },
    {
        "name": "f02n0g08.png-time",
        "quantity": "frequency",
        "unit": "Hz",
        "value": 0.00476500578224659
    },
    {
        "name": "oi1n0g16.png-time",
        "quantity": "frequency",
        "unit": "Hz",
        "value": 0.003106389194726944
    },
    {
        "name": "s06i3p02.png-time",
        "quantity": "frequency",
        "unit": "Hz",
        "value": 0.003922656644135714
    },
    {
        "name": "s07i3p02.png-time",
        "quantity": "frequency",
        "unit": "Hz",
        "value": 0.0046044597402215
    },
    {
        "name": "cdhn2c08.png-time",
        "quantity": "frequency",
        "unit": "Hz",
        "value": 0.013195666950196028
    },
    {
        "name": "f03n2c08.png-time",
        "quantity": "frequency",
        "unit": "Hz",
        "value": 0.004583245608955622
    },
    {
        "name": "f02n2c08.png-time",
        "quantity": "frequency",
        "unit": "Hz",
        "value": 0.00447840616106987
    },
    {
        "name": "cs8n3p08.png-time",
        "quantity": "frequency",
        "unit": "Hz",
        "value": 0.0045190779492259026
    },
    {
        "name": "basn3p04.png-time",
        "quantity": "frequency",
        "unit": "Hz",
        "value": 0.005933098960667849
    },
    {
        "name": "g04n0g16.png-time",
        "quantity": "frequency",
        "unit": "Hz",
        "value": 0.005510367918759584
    },
    {
        "name": "g05n0g16.png-time",
        "quantity": "frequency",
        "unit": "Hz",
        "value": 0.004268782213330269
    },
    {
        "name": "cthn0g04.png-time",
        "quantity": "frequency",
        "unit": "Hz",
        "value": 0.005834357813000679
    },
    {
        "name": "cs3n3p08.png-time",
        "quantity": "frequency",
        "unit": "Hz",
        "value": 0.005847292952239513
    },
    {
        "name": "bgai4a08.png-time",
        "quantity": "frequency",
        "unit": "Hz",
        "value": 0.004449162166565657
    },
    {
        "name": "basi3p08.png-time",
        "quantity": "frequency",
        "unit": "Hz",
        "value": 0.007864154875278473
    },
    {
        "name": "g05n3p04.png-time",
        "quantity": "frequency",
        "unit": "Hz",
        "value": 0.004690228961408138
    },
    {
        "name": "g04n3p04.png-time",
        "quantity": "frequency",
        "unit": "Hz",
        "value": 0.005400126334279776
    },
    {
        "name": "bgan6a16.png-time",
        "quantity": "frequency",
        "unit": "Hz",
        "value": 0.0035289754159748554
    },
    {
        "name": "f04n0g08.png-time",
        "quantity": "frequency",
        "unit": "Hz",
        "value": 0.005238228011876345
    },
    {
        "name": "ct0n0g04.png-time",
        "quantity": "frequency",
        "unit": "Hz",
        "value": 0.0036585922352969646
    },
    {
        "name": "ct1n0g04.png-time",
        "quantity": "frequency",
        "unit": "Hz",
        "value": 0.005271014291793108
    },
    {
        "name": "f04n2c08.png-time",
        "quantity": "frequency",
        "unit": "Hz",
        "value": 0.004872820805758238
    },
    {
        "name": "cten0g04.png-time",
        "quantity": "frequency",
        "unit": "Hz",
        "value": 0.0049286880530416965
    },
    {
        "name": "g03n0g16.png-time",
        "quantity": "frequency",
        "unit": "Hz",
        "value": 0.005230753682553768
    },
    {
        "name": "basn2c16.png-time",
        "quantity": "frequency",
        "unit": "Hz",
        "value": 0.005064616445451975
    },
    {
        "name": "s40n3p04.png-time",
        "quantity": "frequency",
        "unit": "Hz",
        "value": 0.008396930992603302
    },
    {
        "name": "basi4a08.png-time",
        "quantity": "frequency",
        "unit": "Hz",
        "value": 0.0068159690126776695
    },
    {
        "name": "cs5n3p08.png-time",
        "quantity": "frequency",
        "unit": "Hz",
        "value": 0.004517405293881893
    },
    {
        "name": "s37n3p04.png-time",
        "quantity": "frequency",
        "unit": "Hz",
        "value": 0.007656241301447153
    },
    {
        "name": "s36n3p04.png-time",
        "quantity": "frequency",
        "unit": "Hz",
        "value": 0.006924965884536505
    },
    {
        "name": "s01i3p01.png-time",
        "quantity": "frequency",
        "unit": "Hz",
        "value": 0.0060436539351940155
    },
    {
        "name": "g07n2c08.png-time",
        "quantity": "frequency",
        "unit": "Hz",
        "value": 0.004536595195531845
    },
    {
        "name": "basn0g02.png-time",
        "quantity": "frequency",
        "unit": "Hz",
        "value": 0.006764614954590797
    },
    {
        "name": "basn0g16.png-time",
        "quantity": "frequency",
        "unit": "Hz",
        "value": 0.0013324958272278309
    },
    {
        "name": "g25n2c08.png-time",
        "quantity": "frequency",
        "unit": "Hz",
        "value": 0.004250539932399988
    },
    {
        "name": "PngSuite.png-time",
        "quantity": "frequency",
        "unit": "Hz",
        "value": 0.013828922994434834
    },
    {
        "name": "exif2c08.png-time",
        "quantity": "frequency",
        "unit": "Hz",
        "value": 0.007470249198377132
    },
    {
        "name": "basi6a08.png-time",
        "quantity": "frequency",
        "unit": "Hz",
        "value": 0.004334451165050268
    },
    {
        "name": "z03n2c08.png-time",
        "quantity": "frequency",
        "unit": "Hz",
        "value": 0.0038252132944762707
    },
    {
        "name": "s08n3p02.png-time",
        "quantity": "frequency",
        "unit": "Hz",
        "value": 0.0037590772844851017
    },
    {
        "name": "s09n3p02.png-time",
        "quantity": "frequency",
        "unit": "Hz",
        "value": 0.00404246523976326
    },
    {
        "name": "pp0n6a08.png-time",
        "quantity": "frequency",
        "unit": "Hz",
        "value": 0.00488570611923933
    },
    {
        "name": "cs8n2c08.png-time",
        "quantity": "frequency",
        "unit": "Hz",
        "value": 0.004781495314091444
    },
    {
        "name": "f99n0g04.png-time",
        "quantity": "frequency",
        "unit": "Hz",
        "value": 0.005428890697658062
    },
    {
        "name": "ps2n0g08.png-time",
        "quantity": "frequency",
        "unit": "Hz",
        "value": 0.004550352692604065
    },
    {
        "name": "s34i3p04.png-time",
        "quantity": "frequency",
        "unit": "Hz",
        "value": 0.013350070919841528
    },
    {
        "name": "s35i3p04.png-time",
        "quantity": "frequency",
        "unit": "Hz",
        "value": 0.008058901410549879
    },
    {
        "name": "ctzn0g04.png-time",
        "quantity": "frequency",
        "unit": "Hz",
        "value": 0.00631584832444787
    },
    {
        "name": "s03n3p01.png-time",
        "quantity": "frequency",
        "unit": "Hz",
        "value": 0.004646156448870897
    },
    {
        "name": "s02n3p01.png-time",
        "quantity": "frequency",
        "unit": "Hz",
        "value": 0.00415498623624444
    },
    {
        "name": "z09n2c08.png-time",
        "quantity": "frequency",
        "unit": "Hz",
        "value": 0.004976393189281225
    },
    {
        "name": "g10n2c08.png-time",
        "quantity": "frequency",
        "unit": "Hz",
        "value": 0.0053916210308671
    },
    {
        "name": "cm7n0g04.png-time",
        "quantity": "frequency",
        "unit": "Hz",
        "value": 0.005926258862018585
    },
    {
        "name": "ccwn2c08.png-time",
        "quantity": "frequency",
        "unit": "Hz",
        "value": 0.004947643727064133
    },
    {
        "name": "basn0g04.png-time",
        "quantity": "frequency",
        "unit": "Hz",
        "value": 0.003922758158296347
    },
    {
        "name": "g07n0g16.png-time",
        "quantity": "frequency",
        "unit": "Hz",
        "value": 0.0041728550568223
    },
    {
        "name": "basi3p01.png-time",
        "quantity": "frequency",
        "unit": "Hz",
        "value": 0.004995290189981461
    },
    {
        "name": "basn2c08.png-time",
        "quantity": "frequency",
        "unit": "Hz",
        "value": 0.004982804413884878
    },
    {
        "name": "oi9n2c16.png-time",
        "quantity": "frequency",
        "unit": "Hz",
        "value": 0.0070221456699073315
    },
    {
        "name": "basi4a16.png-time",
        "quantity": "frequency",
        "unit": "Hz",
        "value": 0.008153203874826431
    },
    {
        "name": "s04i3p01.png-time",
        "quantity": "frequency",
        "unit": "Hz",
        "value": 0.0056876083835959435
    },
    {
        "name": "ctjn0g04.png-time",
        "quantity": "frequency",
        "unit": "Hz",
        "value": 0.004931692034006119
    },
    {
        "name": "s33n3p04.png-time",
        "quantity": "frequency",
        "unit": "Hz",
        "value": 0.006532157771289349
    },
    {
        "name": "s32n3p04.png-time",
        "quantity": "frequency",
        "unit": "Hz",
        "value": 0.0072480193339288235
    },
    {
        "name": "oi9n0g16.png-time",
        "quantity": "frequency",
        "unit": "Hz",
        "value": 0.003926943987607956
    },
    {
        "name": "g03n2c08.png-time",
        "quantity": "frequency",
        "unit": "Hz",
        "value": 0.005022625904530287
    },
    {
        "name": "basn0g08.png-time",
        "quantity": "frequency",
        "unit": "Hz",
        "value": 0.004069815389811993
    },
    {
        "name": "basi3p02.png-time",
        "quantity": "frequency",
        "unit": "Hz",
        "value": 0.004855995997786522
    },
    {
        "name": "tp0n2c08.png-time",
        "quantity": "frequency",
        "unit": "Hz",
        "value": 0.004804045893251896
    },
    {
        "name": "bgan6a08.png-time",
        "quantity": "frequency",
        "unit": "Hz",
        "value": 0.004235072061419487
    },
    {
        "name": "oi2n2c16.png-time",
        "quantity": "frequency",
        "unit": "Hz",
        "value": 0.005758894607424736
    },
    {
        "name": "f00n0g08.png-time",
        "quantity": "frequency",
        "unit": "Hz",
        "value": 0.004312172997742891
    },
    {
        "name": "f01n0g08.png-time",
        "quantity": "frequency",
        "unit": "Hz",
        "value": 0.007929400075227022
    },
    {
        "name": "s05i3p02.png-time",
        "quantity": "frequency",
        "unit": "Hz",
        "value": 0.004644168075174093
    },
    {
        "name": "oi2n0g16.png-time",
        "quantity": "frequency",
        "unit": "Hz",
        "value": 0.0041341399773955345
    },
    {
        "name": "f00n2c08.png-time",
        "quantity": "frequency",
        "unit": "Hz",
        "value": 0.004869003780186176
    },
    {
        "name": "f01n2c08.png-time",
        "quantity": "frequency",
        "unit": "Hz",
        "value": 0.005563661921769381
    },
    {
        "name": "s39n3p04.png-time",
        "quantity": "frequency",
        "unit": "Hz",
        "value": 0.011945464182645082
    },
    {
        "name": "s38n3p04.png-time",
        "quantity": "frequency",
        "unit": "Hz",
        "value": 0.006335088983178139
    },
    {
        "name": "tp0n0g08.png-time",
        "quantity": "frequency",
        "unit": "Hz",
        "value": 0.006120726931840181
    },
    {
        "name": "cdun2c08.png-time",
        "quantity": "frequency",
        "unit": "Hz",
        "value": 0.0036784508265554905
    },
    {
        "name": "g10n0g16.png-time",
        "quantity": "frequency",
        "unit": "Hz",
        "value": 0.004317162558436394
    },
    {
        "name": "ch1n3p04.png-time",
        "quantity": "frequency",
        "unit": "Hz",
        "value": 0.005080345086753368
    },
    {
        "name": "ps2n2c16.png-time",
        "quantity": "frequency",
        "unit": "Hz",
        "value": 0.003976070787757635
    },
    {
        "name": "basi3p04.png-time",
        "quantity": "frequency",
        "unit": "Hz",
        "value": 0.004049540963023901
    },
    {
        "name": "cs3n2c16.png-time",
        "quantity": "frequency",
        "unit": "Hz",
        "value": 0.006028810981661081
    },
    {
        "name": "s06n3p02.png-time",
        "quantity": "frequency",
        "unit": "Hz",
        "value": 0.007072017062455416
    },
    {
        "name": "s07n3p02.png-time",
        "quantity": "frequency",
        "unit": "Hz",
        "value": 0.0056392778642475605
    },
    {
        "name": "g25n0g16.png-time",
        "quantity": "frequency",
        "unit": "Hz",
        "value": 0.005801782943308353
    },
    {
        "name": "z06n2c08.png-time",
        "quantity": "frequency",
        "unit": "Hz",
        "value": 0.00402872497215867
    },
    {
        "name": "basi6a16.png-time",
        "quantity": "frequency",
        "unit": "Hz",
        "value": 0.007292914669960737
    },
    {
        "name": "cm9n0g04.png-time",
        "quantity": "frequency",
        "unit": "Hz",
        "value": 0.006499054841697216
    },
    {
        "name": "cdsn2c08.png-time",
        "quantity": "frequency",
        "unit": "Hz",
        "value": 0.004878514911979437
    },
    {
        "name": "ps1n0g08.png-time",
        "quantity": "frequency",
        "unit": "Hz",
        "value": 0.004287655930966139
    },
    {
        "name": "basi0g02.png-time",
        "quantity": "frequency",
        "unit": "Hz",
        "value": 0.0052246651612222195
    },
    {
        "name": "basi0g16.png-time",
        "quantity": "frequency",
        "unit": "Hz",
        "value": 0.005506122950464487
    },
    {
        "name": "basn4a08.png-time",
        "quantity": "frequency",
        "unit": "Hz",
        "value": 0.0048778606578707695
    },
    {
        "name": "s37i3p04.png-time",
        "quantity": "frequency",
        "unit": "Hz",
        "value": 0.006519322749227285
    },
    {
        "name": "s36i3p04.png-time",
        "quantity": "frequency",
        "unit": "Hz",
        "value": 0.005255259107798338
    },
    {
        "name": "s01n3p01.png-time",
        "quantity": "frequency",
        "unit": "Hz",
        "value": 0.006657927762717009
    },
    {
        "name": "s40i3p04.png-time",
        "quantity": "frequency",
        "unit": "Hz",
        "value": 0.008063158020377159
    },
    {
        "name": "g25n3p04.png-time",
        "quantity": "frequency",
        "unit": "Hz",
        "value": 0.006196293048560619
    },
    {
        "name": "tp0n3p08.png-time",
        "quantity": "frequency",
        "unit": "Hz",
        "value": 0.004493481945246458
    },
    {
        "name": "basi2c16.png-time",
        "quantity": "frequency",
        "unit": "Hz",
        "value": 0.005174550693482161
    },
    {
        "name": "pp0n2c16.png-time",
        "quantity": "frequency",
        "unit": "Hz",
        "value": 0.009279416874051094
    },
    {
        "name": "g10n3p04.png-time",
        "quantity": "frequency",
        "unit": "Hz",
        "value": 0.004445081576704979
    },
    {
        "name": "basn3p08.png-time",
        "quantity": "frequency",
        "unit": "Hz",
        "value": 0.005925973877310753
    },
    {
        "name": "z00n2c08.png-time",
        "quantity": "frequency",
        "unit": "Hz",
        "value": 0.0047228350304067135
    },
    {
        "name": "basi0g04.png-time",
        "quantity": "frequency",
        "unit": "Hz",
        "value": 0.0049986205995082855
    },
    {
        "name": "s34n3p04.png-time",
        "quantity": "frequency",
        "unit": "Hz",
        "value": 0.007012748159468174
    },
    {
        "name": "s35n3p04.png-time",
        "quantity": "frequency",
        "unit": "Hz",
        "value": 0.007201286032795906
    },
    {
        "name": "s03i3p01.png-time",
        "quantity": "frequency",
        "unit": "Hz",
        "value": 0.0055756838992238045
    },
    {
        "name": "s02i3p01.png-time",
        "quantity": "frequency",
        "unit": "Hz",
        "value": 0.0036693732254207134
    },
    {
        "name": "s08i3p02.png-time",
        "quantity": "frequency",
        "unit": "Hz",
        "value": 0.005483265034854412
    },
    {
        "name": "s09i3p02.png-time",
        "quantity": "frequency",
        "unit": "Hz",
        "value": 0.004906811285763979
    },
    {
        "name": "g05n2c08.png-time",
        "quantity": "frequency",
        "unit": "Hz",
        "value": 0.005278417840600014
    },
    {
        "name": "g04n2c08.png-time",
        "quantity": "frequency",
        "unit": "Hz",
        "value": 0.004960903897881508
    },
    {
        "name": "ch2n3p08.png-time",
        "quantity": "frequency",
        "unit": "Hz",
        "value": 0.009221625048667192
    },
    {
        "name": "bgai4a16.png-time",
        "quantity": "frequency",
        "unit": "Hz",
        "value": 0.003094285260885954
    },
    {
        "name": "cdfn2c08.png-time",
        "quantity": "frequency",
        "unit": "Hz",
        "value": 0.005374003201723099
    },
    {
        "name": "basn6a08.png-time",
        "quantity": "frequency",
        "unit": "Hz",
        "value": 0.003311836626380682
    },
    {
        "name": "g07n3p04.png-time",
        "quantity": "frequency",
        "unit": "Hz",
        "value": 0.004936769139021635
    },
    {
        "name": "oi4n2c16.png-time",
        "quantity": "frequency",
        "unit": "Hz",
        "value": 0.005644289311021566
    },
    {
        "name": "oi4n0g16.png-time",
        "quantity": "frequency",
        "unit": "Hz",
        "value": 0.00519766379147768
    },
    {
        "name": "ctfn0g04.png-time",
        "quantity": "frequency",
        "unit": "Hz",
        "value": 0.005365240853279829
    },
    {
        "name": "ctgn0g04.png-time",
        "quantity": "frequency",
        "unit": "Hz",
        "value": 0.0042556291446089745
    }
]